logger/__init__.py
logger/conf.py
logger/example.py
logger/logging_functions.py
logger/setup.py
ldmlogger-0.0.11.dist-info/LICENSE.txt
ldmlogger-0.0.11.dist-info/METADATA
ldmlogger-0.0.11.dist-info/WHEEL
ldmlogger-0.0.11.dist-info/top_level.txt
ldmlogger-0.0.11.dist-info/RECORD
