Metadata-Version: 2.1
Name: ldmlogger
Version: 0.0.11
Summary: Python client side functions for working with LDM framework.
Home-page: https://github.com/IMCS-DL4media/LDM/tree/master/logger
Author: Arturs
Author-email: arturs.sprogis@gmail.com
License: MIT
Download-URL: https://pypi.org/project/ldmlogger/
Keywords: LDM,Python 3,ML life cycle
Platform: UNKNOWN
Requires-Dist: requests
Requires-Dist: pathspec
